openirisapi/__init__.py
openirisapi/io_analysis.py
openirisapi/openirisapi.py
openirisapi/utilities.py
openirisapi-0.0.3.1.dist-info/LICENCE.txt
openirisapi-0.0.3.1.dist-info/METADATA
openirisapi-0.0.3.1.dist-info/WHEEL
openirisapi-0.0.3.1.dist-info/top_level.txt
openirisapi-0.0.3.1.dist-info/RECORD
