Metadata-Version: 2.1
Name: openirisapi
Version: 0.0.3.1
Summary: A very basic API built upon requests for openiris.io
Home-page: https://gitlab.in2p3.fr/sotirios.PAPADIAMANTIS/openirisAPI
Author: Sotiris Papadiamantis
Author-email: sotirios.papadiamantis@univ-amu.fr
Classifier: Development Status :: 3 - Alpha
Classifier: Intended Audience :: Education
Classifier: Topic :: Software Development :: Build Tools
Classifier: License :: OSI Approved :: MIT License
Classifier: Programming Language :: Python :: 3.0
Requires-Python: >=3.7
License-File: LICENCE.txt
Requires-Dist: requests
Requires-Dist: pandas
